{
    "title": "SyncRidderkerkOpenWooAction",
    "$id": "https://commongateway.nl/woo.SyncRidderkerkOpenWooAction.action.json",
    "$schema": "https://docs.commongateway.nl/schemas/Action.schema.json",
    "version": "0.0.2",
    "listens": ["woo.default.listens"],
    "configuration": {
        "oidn": "ridderkerk",
        "portalUrl": "https://conductionnl.github.io/woo-website-ridderkerk",
        "source": "https://commongateway.woo.nl/source/ridderkerk.openwoo.source.json",
        "schema": "https://commongateway.nl/woo.publicatie.schema.json",
        "mapping": "https://commongateway.nl/mapping/woo.openWooToWoo.mapping.json",
        "sourceType": "openWoo",
        "bestuursorgaan": "Gemeente Ridderkerk",
        "sourceEndpoint": "/owc/openwoo/v1/items"
    },
    "conditions":
    {
        "==": [1, 1]
    },
    "class": "CommonGateway\\WOOBundle\\ActionHandler\\SyncOpenWooHandler"
}
